{
  "entity.happy_ghast.name": "Gelukkige Ghast ",
  "item.spawn_egg.entity.happy_ghast.name": "Gelukkig Ghastspawnei ",
  "tile.dried_ghast.name": "Gedroogde Ghast ",
  "itemGroup.name.harnesses": "Harnassen ",
  "item.black_harness.name": "Zwart harnas ",
  "item.blue_harness.name": "Blauw harnas ",
  "item.brown_harness.name": "Bruin harnas ",
  "item.cyan_harness.name": "Cyaanblauw harnas ",
  "item.gray_harness.name": "Grijs harnas ",
  "item.green_harness.name": "Groen harnas ",
  "item.light_blue_harness.name": "Lichtblauw harnas ",
  "item.light_gray_harness.name": "Lichtgrijs harnas ",
  "item.lime_harness.name": "Limoengroen harnas ",
  "item.magenta_harness.name": "Magenta harnas ",
  "item.orange_harness.name": "Oranje harnas ",
  "item.pink_harness.name": "Roze harnas ",
  "item.purple_harness.name": "Paars harnas ",
  "item.red_harness.name": "Rood harnas ",
  "item.white_harness.name": "Wit harnas ",
  "item.yellow_harness.name": "Geel harnas ",
  "action.hint.exit.happy_ghast": "Tik op sluipen om af te stappen ",
  "action.hint.exit.scheme.happy_ghast": "Tik op sluipen om af te stappen ",
  "action.hint.exit.console.happy_ghast": "Druk op :_input_key.sneak: om af te stappen "
}