{
  "skinpack.CyberSpaceSkinPack": "Cyber Space Team Pack",
  "skin.CyberSpaceSkinPack.BlueKnight": "Blue Knight",
  "skin.CyberSpaceSkinPack.BlueMech": "Blue Mech",
  "skin.CyberSpaceSkinPack.BlueScout": "Blue Scout",
  "skin.CyberSpaceSkinPack.GreenKnight": "Green Knight",
  "skin.CyberSpaceSkinPack.GreenMech": "Green Mech",
  "skin.CyberSpaceSkinPack.GreenScout": "Green Scout",
  "skin.CyberSpaceSkinPack.RedKnight": "Red Knight",
  "skin.CyberSpaceSkinPack.RedMech": "Red Mech",
  "skin.CyberSpaceSkinPack.RedScout": "Red Scout",
  "skin.CyberSpaceSkinPack.YellowKnight": "Yellow Knight",
  "skin.CyberSpaceSkinPack.YellowMech": "Yellow Mech",
  "skin.CyberSpaceSkinPack.YellowScout": "Yellow Scout"
}