{
  "tile.sculk_sensor.name": "Скалковий детектор вібрацій",
  "tile.sculk.name": "Скалк",
  "tile.sculk_vein.name": "Скалкова жила",
  "tile.sculk_catalyst.name": "Скалковий каталізатор",
  "tile.sculk_shrieker.name": "Скалковий крикун",
  "tile.reinforced_deepslate.name": "Посилений глибинний сланець",
  "itemGroup.name.sculk": "Скалк",
  "effect.darkness": "Темрява",
  "entity.frog.name": "Жаба",
  "entity.tadpole.name": "Пуголовок",
  "item.spawn_egg.entity.warden.name": "Страж яйця призову",
  "entity.warden.name": "Страж",
  "entity.allay.name": "Служка",
  "item.spawn_egg.entity.allay.name": "Яйце призову служки",
  "action.interact.allay": "Служка",
  "item.bucketTadpole.name": "Відро пуголовків",
  "item.spawn_egg.entity.frog.name": "Призвати жабу",
  "item.spawn_egg.entity.tadpole.name": "Призвати пуголовка",
  "tile.frog_spawn.name": "Точка появи жаби",
  "tile.pearlescent_froglight.name": "Перламутровий жабосвіт",
  "tile.verdant_froglight.name": "Зелений жабосвіт",
  "tile.ochre_froglight.name": "Вохряний жабосвіт",
  "tile.mud.name": "Бруд",
  "tile.packed_mud.name": "Пакет бруду",
  "tile.mud_bricks.name": "Цегла з бруду",
  "tile.mud_brick_slab.name": "Плита з глиняної цегли",
  "tile.mud_brick_double_slab": "Подвійна плита з глиняної цегли",
  "tile.mud_brick_stairs.name": "Сходи з глиняної цегли",
  "tile.mud_brick_wall.name": "Стіна з глиняної цегли",
  "item.chest_boat.oak.name": "Дубовий човен зі скринею",
  "item.chest_boat.spruce.name": "Човен із хвойного дерева зі скринею",
  "item.chest_boat.birch.name": "Березовий човен зі скринею",
  "item.chest_boat.jungle.name": "Човен із тропічного дерева зі скринею",
  "item.chest_boat.acacia.name": "Човен з акації зі скринею",
  "item.chest_boat.big_oak.name": "Човен із темного дуба зі скринею",
  "item.chest_boat.mangrove.name": "Мангровий човен зі скринею",
  "action.hint.exit.chest_boat": "Торкніться кнопки \"Стрибнути\", щоб зійти з човна",
  "action.hint.exit.console.chest_boat": "Натисніть :_input_key.jump:, щоб зійти з човна",
  "entity.chest_boat.name": "Човен зі скринею",
  "feature.ancientcity": "Стародавнє місто"
}